game_of_thrones/__init__.py
game_of_thrones/main.py
name_of_thrones-0.2.10.dist-info/LICENCE
name_of_thrones-0.2.10.dist-info/METADATA
name_of_thrones-0.2.10.dist-info/WHEEL
name_of_thrones-0.2.10.dist-info/entry_points.txt
name_of_thrones-0.2.10.dist-info/top_level.txt
name_of_thrones-0.2.10.dist-info/RECORD
