Metadata-Version: 2.1
Name: name-of-thrones
Version: 0.2.10
Summary: Command line tool to generate words that sound like characters from Game of Thrones. Good for naming projects, servers and stray cats.
Home-page: https://codeberg.org/Dokana/Name-of-Thrones
Author: Matt Deacalion Stevens
Author-email: matt@dirtymonkey.co.uk
License: MIT
Keywords: game of thrones naming namer project tools
Classifier: Development Status :: 4 - Beta
Classifier: Environment :: Console
Classifier: Intended Audience :: Developers
Classifier: Intended Audience :: End Users/Desktop
Classifier: License :: OSI Approved :: MIT License
Classifier: Natural Language :: English
Classifier: Operating System :: POSIX :: Linux
Classifier: Operating System :: POSIX :: BSD
Classifier: Programming Language :: Python :: 2.7
Classifier: Programming Language :: Python :: 3.2
Classifier: Programming Language :: Python :: 3.3
Classifier: Programming Language :: Python :: 3.4
Classifier: Topic :: Utilities
License-File: LICENCE
Requires-Dist: colorama (>=0.3.1)
Requires-Dist: docopt (>=0.6.2)
